openapi_generator.py
my_openapi_lib-0.1.0.dist-info/METADATA
my_openapi_lib-0.1.0.dist-info/WHEEL
my_openapi_lib-0.1.0.dist-info/entry_points.txt
my_openapi_lib-0.1.0.dist-info/top_level.txt
my_openapi_lib-0.1.0.dist-info/RECORD
