Metadata-Version: 2.2
Name: my_openapi_lib
Version: 0.1.0
Summary: A library to generate OpenAPI specs from Python FastAPI projects.
Author-email: Lior Trachtman <lior.trachtman@gmail.com>
Requires-Python: >=3.7
Requires-Dist: openapi-specgen
Requires-Dist: fastapi
Requires-Dist: pydantic
Requires-Dist: pyyaml
Requires-Dist: jsonschema
